validators/OgrnValidator.py
validators/SnilsValidator.py
validators/__init__.py
ru_value_validator-0.1.1.dist-info/METADATA
ru_value_validator-0.1.1.dist-info/WHEEL
ru_value_validator-0.1.1.dist-info/top_level.txt
ru_value_validator-0.1.1.dist-info/RECORD
