Metadata-Version: 2.4
Name: ru-value-validator
Version: 0.1.1
Summary: Валидация для российских идентификаторов
Author-email: Кудрин Артем <yorkwilsa@gmail.com>
Project-URL: Homepage, https://github.com/Yorkwilsa/ru-value-validator
Requires-Python: >=3.6
